neurokits/__init__.py
neurokits/PET2Mesh.py
neurokits/template/MNI152_T1_1mm.nii
neurokits-0.1.2.dist-info/LICENSE
neurokits-0.1.2.dist-info/METADATA
neurokits-0.1.2.dist-info/WHEEL
neurokits-0.1.2.dist-info/RECORD
