Metadata-Version: 2.3
Name: NeuroKits
Version: 0.1.2
Summary: Some useful functions for processing neuroimaging data.
License: MIT
Author: Kun Jiang
Author-email: kevin.jiang0521@gmail.com
Requires-Python: >=3.8
Classifier: License :: OSI Approved :: MIT License
Classifier: Programming Language :: Python :: 3
Classifier: Programming Language :: Python :: 3.8
Classifier: Programming Language :: Python :: 3.9
Classifier: Programming Language :: Python :: 3.10
Classifier: Programming Language :: Python :: 3.11
Classifier: Programming Language :: Python :: 3.12
Classifier: Programming Language :: Python :: 3.13
Requires-Dist: numpy (>=1.21)
Project-URL: Homepage, https://pypi.org/project/NeuroKits/
